clicolor/__init__.py
clicolor/cli.py
clicolor-1.0.7.dist-info/LICENSE
clicolor-1.0.7.dist-info/METADATA
clicolor-1.0.7.dist-info/WHEEL
clicolor-1.0.7.dist-info/top_level.txt
clicolor-1.0.7.dist-info/RECORD
