Metadata-Version: 2.1
Name: clicolor
Version: 1.0.7
Summary: Quick python reference for terminal color escape codes
Home-page: https://github.com/camas/clicolor
Author: Camas
Author-email: camas@hotmail.co.uk
License: UNKNOWN
Platform: UNKNOWN
Classifier: Programming Language :: Python :: 3
Classifier: License :: OSI Approved :: MIT License
Classifier: Operating System :: OS Independent
Requires-Python: >=3.7
